{
  "entityType" : "DEVICE",
  "entity" : {
    "additionalInfo" : { },
    "customerId" : {
      "entityType" : "CUSTOMER",
      "id" : "13814000-1dd2-11b2-8080-808080808080"
    },
    "deviceData" : {
      "configuration" : {
        "type" : "DEFAULT"
      },
      "transportConfiguration" : {
        "type" : "DEFAULT"
      }
    },
    "deviceProfileId" : {
      "entityType" : "DEVICE_PROFILE",
      "id" : "59c875d0-6d56-11f0-aa5d-9d41b7ed1450"
    },
    "externalId" : {
      "entityType" : "DEVICE",
      "id" : "df1393f0-6df6-11f0-aa5d-9d41b7ed1450"
    },
    "firmwareId" : null,
    "id" : {
      "entityType" : "DEVICE",
      "id" : "df1393f0-6df6-11f0-aa5d-9d41b7ed1450"
    },
    "label" : null,
    "name" : "500150266 ",
    "ownerId" : null,
    "softwareId" : null,
    "type" : "NEPTUNE-360"
  },
  "credentials" : {
    "credentialsId" : "fR93206nAVo2PHyH1xmO",
    "credentialsType" : "ACCESS_TOKEN",
    "credentialsValue" : null
  },
  "relations" : [ ],
  "attributes" : {
    "SERVER_SCOPE" : [ {
      "booleanValue" : false,
      "doubleValue" : null,
      "jsonValue" : null,
      "key" : "active",
      "lastUpdateTs" : 1753957363057,
      "longValue" : null,
      "strValue" : null
    }, {
      "booleanValue" : null,
      "doubleValue" : null,
      "jsonValue" : null,
      "key" : "inactivityAlarmTime",
      "lastUpdateTs" : 1753957363050,
      "longValue" : 1753957363049,
      "strValue" : null
    } ],
    "SHARED_SCOPE" : [ ]
  },
  "calculatedFields" : [ ]
}