{
  "entityType" : "RULE_CHAIN",
  "entity" : {
    "additionalInfo" : {
      "description" : ""
    },
    "configuration" : null,
    "debugMode" : false,
    "externalId" : null,
    "firstRuleNodeId" : null,
    "id" : {
      "entityType" : "RULE_CHAIN",
      "id" : "3ccf4e60-a067-11f0-9289-6f201dc104bf"
    },
    "name" : "LatinTest",
    "root" : false,
    "type" : "CORE"
  },
  "metaData" : {
    "connections" : [ {
      "fromIndex" : 0,
      "toIndex" : 1,
      "type" : "Success"
    } ],
    "firstNodeIndex" : null,
    "nodes" : [ {
      "additionalInfo" : {
        "description" : "",
        "layoutX" : 51,
        "layoutY" : 251
      },
      "configuration" : {
        "msgCount" : 1,
        "periodInSeconds" : 60,
        "scriptLang" : "TBEL",
        "jsScript" : "var msg = { temp: 42, humidity: 77 };\nvar metadata = { data: 40 };\nvar msgType = \"POST_TELEMETRY_REQUEST\";\n\nreturn { msg: msg, metadata: metadata, msgType: msgType };",
        "tbelScript" : "var msg = { temp: 42, humidity: 77 };\nvar metadata = { data: 40 };\nvar msgType = \"POST_TELEMETRY_REQUEST\";\n\nreturn { msg: msg, metadata: metadata, msgType: msgType };",
        "originatorId" : null,
        "originatorType" : "RULE_NODE"
      },
      "configurationVersion" : 2,
      "createdTime" : 0,
      "debugSettings" : null,
      "externalId" : null,
      "id" : {
        "entityType" : "RULE_NODE",
        "id" : "73063e30-a067-11f0-8c82-b38e8bd8f7b8"
      },
      "name" : "test",
      "queueName" : null,
      "ruleChainId" : null,
      "singletonMode" : false,
      "type" : "org.thingsboard.rule.engine.debug.TbMsgGeneratorNode"
    }, {
      "additionalInfo" : {
        "description" : "",
        "layoutX" : 361,
        "layoutY" : 253
      },
      "configuration" : {
        "useConfigFromMessage" : false,
        "config" : {
          "reportTemplateId" : {
            "entityType" : "REPORT_TEMPLATE",
            "id" : "fc60f590-a061-11f0-9289-6f201dc104bf"
          },
          "timezone" : "Europe/Kiev",
          "userId" : {
            "entityType" : "USER",
            "id" : "1495c070-fdae-11ef-bca0-9d823f5ae12e"
          },
          "targets" : [ ],
          "notificationTemplateId" : null
        }
      },
      "configurationVersion" : 0,
      "createdTime" : 0,
      "debugSettings" : null,
      "externalId" : null,
      "id" : {
        "entityType" : "RULE_NODE",
        "id" : "7306b360-a067-11f0-8c82-b38e8bd8f7b8"
      },
      "name" : "test123",
      "queueName" : null,
      "ruleChainId" : null,
      "singletonMode" : false,
      "type" : "org.thingsboard.rule.engine.report.TbGenerateReportV2Node"
    } ],
    "ruleChainConnections" : null
  },
  "relations" : [ ],
  "attributes" : {
    "SERVER_SCOPE" : [ ]
  }
}