{
  "entityType" : "DEVICE_PROFILE",
  "entity" : {
    "default" : false,
    "defaultDashboardId" : null,
    "defaultEdgeRuleChainId" : null,
    "defaultQueueName" : null,
    "defaultRuleChainId" : null,
    "description" : "",
    "externalId" : {
      "entityType" : "DEVICE_PROFILE",
      "id" : "ed1dffa0-4838-11f0-b5b5-3b453a0b42b3"
    },
    "firmwareId" : null,
    "id" : {
      "entityType" : "DEVICE_PROFILE",
      "id" : "ed1dffa0-4838-11f0-b5b5-3b453a0b42b3"
    },
    "image" : null,
    "name" : "test223",
    "profileData" : {
      "alarms" : null,
      "configuration" : {
        "type" : "DEFAULT"
      },
      "provisionConfiguration" : {
        "type" : "DISABLED",
        "provisionDeviceSecret" : null
      },
      "transportConfiguration" : {
        "type" : "LWM2M",
        "bootstrap" : [ {
          "securityMode" : "NO_SEC",
          "binding" : "U",
          "bootstrapServerAccountTimeout" : 0,
          "bootstrapServerIs" : false,
          "clientHoldOffTime" : 1,
          "defaultMinPeriod" : 1,
          "host" : "0.0.0.0",
          "lifetime" : 300,
          "notifIfDisabled" : true,
          "port" : 5685,
          "serverCertificate" : "",
          "serverPublicKey" : "",
          "shortServerId" : 123
        }, {
          "securityMode" : "NO_SEC",
          "binding" : "U",
          "bootstrapServerAccountTimeout" : 0,
          "bootstrapServerIs" : false,
          "clientHoldOffTime" : 1,
          "defaultMinPeriod" : 1,
          "host" : "0.0.0.1",
          "lifetime" : 300,
          "notifIfDisabled" : true,
          "port" : 5685,
          "serverCertificate" : null,
          "serverPublicKey" : "",
          "shortServerId" : 1234
        } ],
        "bootstrapServerUpdateEnable" : false,
        "clientLwM2mSettings" : {
          "clientOnlyObserveAfterConnect" : 1,
          "defaultObjectIDVer" : "1.0",
          "edrxCycle" : 81000,
          "fwUpdateResource" : null,
          "fwUpdateStrategy" : 1,
          "pagingTransmissionWindow" : 10000,
          "powerMode" : "DRX",
          "psmActivityTimer" : 10000,
          "swUpdateResource" : null,
          "swUpdateStrategy" : 1,
          "useObject19ForOtaInfo" : false
        },
        "observeAttr" : {
          "attribute" : [ "/10243_2.0/0/1", "/10243_2.0/0/5" ],
          "attributeLwm2m" : { },
          "keyName" : {
            "/10243_2.0/0/1" : "modelNumber",
            "/10243_2.0/0/3" : "description",
            "/10243_2.0/0/5" : "current"
          },
          "observe" : [ ],
          "observeStrategy" : "SINGLE",
          "telemetry" : [ "/10243_2.0/0/3" ]
        }
      }
    },
    "provisionDeviceKey" : null,
    "provisionType" : "DISABLED",
    "softwareId" : null,
    "transportType" : "LWM2M",
    "type" : "DEFAULT"
  },
  "relations" : [ ],
  "attributes" : {
    "SERVER_SCOPE" : [ ]
  },
  "calculatedFields" : [ ]
}